MedoEncTT/__init__.py
MedoEncTT-3.1.dist-info/METADATA
MedoEncTT-3.1.dist-info/WHEEL
MedoEncTT-3.1.dist-info/top_level.txt
MedoEncTT-3.1.dist-info/RECORD
