Metadata-Version: 2.1
Name: MedoEncTT
Version: 3.1
Summary: A brief description of my library
Home-page: https://github.com/MohammedNajih/signer-zziqz
Author: Mohamed Almuswi
Author-email: mmaa58027@gmail.com
License: MIT
Classifier: Programming Language :: Python :: 3
Classifier: License :: OSI Approved :: MIT License
Classifier: Operating System :: OS Independent
Requires-Python: >=3.6
